slice_a_portion/__init__.py
slice_a_portion-0.1.dist-info/LICENSE
slice_a_portion-0.1.dist-info/METADATA
slice_a_portion-0.1.dist-info/WHEEL
slice_a_portion-0.1.dist-info/top_level.txt
slice_a_portion-0.1.dist-info/RECORD
