Metadata-Version: 2.1
Name: slice-a-portion
Version: 0.1
Summary: get the i/n slice of a sequence
Author: Martín Gaitán
License: Apache-2.0
Project-URL: Homepage, https://github.com/mgaitan/slice-a-portion
Project-URL: Changelog, https://github.com/mgaitan/slice-a-portion/releases
Project-URL: Issues, https://github.com/mgaitan/slice-a-portion/issues
Project-URL: CI, https://github.com/mgaitan/slice-a-portion/actions
Classifier: License :: OSI Approved :: Apache Software License
Requires-Python: >=3.8
License-File: LICENSE
Provides-Extra: test
Requires-Dist: pytest ; extra == 'test'
